[
  {
    "slug": "mountain-vista-hs",
    "name": "Mountain Vista High School",
    "short_name": "Mountain Vista HS",
    "city": "Highlands Ranch, CO",
    "address": "Mountain Vista High School, Highlands Ranch, CO",
    "parking": "Use school parking areas near the baseball complex. Follow posted event signage.",
    "seating": "Bleacher and standing-room seating may be available. Fans may wish to bring portable chairs where permitted.",
    "concessions": "Concession availability varies by event.",
    "restrooms": "Restroom access may vary by event and facility schedule.",
    "dimensions": "Field dimensions to be added.",
    "photo": "",
    "notes": "Primary Colorado Tribe home venue."
  },
  {
    "slug": "doherty-hs",
    "name": "Doherty High School",
    "short_name": "Doherty HS",
    "city": "Colorado Springs, CO",
    "address": "Doherty High School, Colorado Springs, CO",
    "parking": "Use school parking areas and follow posted event signage.",
    "seating": "Bleacher and standing-room seating may be available.",
    "concessions": "Concession availability varies by event.",
    "restrooms": "Restroom access may vary by event.",
    "dimensions": "Field dimensions to be added.",
    "photo": "",
    "notes": "Opening Day venue."
  },
  {
    "slug": "castle-view-hs",
    "name": "Castle View High School",
    "short_name": "Castle View HS",
    "city": "Castle Rock, CO",
    "address": "Castle View High School, Castle Rock, CO",
    "parking": "Use school parking areas and follow posted event signage.",
    "seating": "Bleacher and standing-room seating may be available.",
    "concessions": "Concession availability varies by event.",
    "restrooms": "Restroom access may vary by event.",
    "dimensions": "Field dimensions to be added.",
    "photo": "",
    "notes": ""
  },
  {
    "slug": "thompson-valley-hs",
    "name": "Thompson Valley High School",
    "short_name": "Thompson Valley HS",
    "city": "Loveland, CO",
    "address": "Thompson Valley High School, Loveland, CO",
    "parking": "Use school parking areas and follow posted event signage.",
    "seating": "Bleacher and standing-room seating may be available.",
    "concessions": "Concession availability varies by event.",
    "restrooms": "Restroom access may vary by event.",
    "dimensions": "Field dimensions to be added.",
    "photo": "",
    "notes": ""
  },
  {
    "slug": "denver-christian-hs",
    "name": "Denver Christian School",
    "short_name": "Denver Christian HS",
    "city": "Lakewood, CO",
    "address": "Denver Christian School, Lakewood, CO",
    "parking": "Use school parking areas and follow posted event signage.",
    "seating": "Bleacher and standing-room seating may be available.",
    "concessions": "Concession availability varies by event.",
    "restrooms": "Restroom access may vary by event.",
    "dimensions": "Field dimensions to be added.",
    "photo": "",
    "notes": ""
  },
  {
    "slug": "northeastern-jc",
    "name": "Northeastern Junior College",
    "short_name": "Northeastern JC",
    "city": "Sterling, CO",
    "address": "Northeastern Junior College, Sterling, CO",
    "parking": "Use campus event parking and follow posted signage.",
    "seating": "Stadium or bleacher seating may be available.",
    "concessions": "Concession availability varies by event.",
    "restrooms": "Restroom access may vary by event.",
    "dimensions": "Field dimensions to be added.",
    "photo": "",
    "notes": "All-Star Game venue."
  },
  {
    "slug": "arvada-west-hs",
    "name": "Arvada West High School",
    "short_name": "Arvada West HS",
    "city": "Arvada, CO",
    "address": "Arvada West High School, Arvada, CO",
    "parking": "Use school parking areas and follow posted event signage.",
    "seating": "Bleacher and standing-room seating may be available.",
    "concessions": "Concession availability varies by event.",
    "restrooms": "Restroom access may vary by event.",
    "dimensions": "Field dimensions to be added.",
    "photo": "",
    "notes": ""
  },
  {
    "slug": "university-hs",
    "name": "University High School",
    "short_name": "University HS",
    "city": "Greeley, CO",
    "address": "University High School, Greeley, CO",
    "parking": "Use school parking areas and follow posted event signage.",
    "seating": "Bleacher and standing-room seating may be available.",
    "concessions": "Concession availability varies by event.",
    "restrooms": "Restroom access may vary by event.",
    "dimensions": "Field dimensions to be added.",
    "photo": "",
    "notes": ""
  },
  {
    "slug": "four-rivers-stadium",
    "name": "4 Rivers Equipment Stadium",
    "short_name": "4 Rivers Stadium",
    "city": "Windsor, CO",
    "address": "4 Rivers Equipment Stadium, Windsor, CO",
    "parking": "Use stadium event parking and follow posted signage.",
    "seating": "Stadium seating available.",
    "concessions": "Concession availability varies by event.",
    "restrooms": "Restroom access available during events.",
    "dimensions": "Field dimensions to be added.",
    "photo": "",
    "notes": ""
  },
  {
    "slug": "douglas-county-hs",
    "name": "Douglas County High School",
    "short_name": "Douglas County HS",
    "city": "Castle Rock, CO",
    "address": "Douglas County High School, Castle Rock, CO",
    "parking": "Use school parking areas and follow posted event signage.",
    "seating": "Bleacher and standing-room seating may be available.",
    "concessions": "Concession availability varies by event.",
    "restrooms": "Restroom access may vary by event.",
    "dimensions": "Field dimensions to be added.",
    "photo": "",
    "notes": ""
  }
]