[
  {
    "number": "1",
    "name": "Player Name",
    "slug": "player-1",
    "position": "INF",
    "college": "College / University",
    "hometown": "Hometown, CO",
    "height": "6'0\"",
    "weight": "185",
    "bats": "R",
    "throws": "R",
    "class": "Sophomore",
    "major": "Major",
    "photo": "",
    "college_logo": "",
    "high_school": "",
    "action_photo": "",
    "bio": "",
    "why_tribe": "",
    "coach_comments": "",
    "development_goals": [],
    "awards": [],
    "social": {
      "instagram": "",
      "x": ""
    },
    "qa": {
      "favorite_mlb_player": "",
      "favorite_team": "",
      "favorite_baseball_memory": "",
      "walkup_song": "",
      "favorite_food": "",
      "hidden_talent": ""
    },
    "gamechanger_name": "Player Name",
    "gamechanger_player_id": ""
  },
  {
    "number": "2",
    "name": "Player Name",
    "slug": "player-2",
    "position": "OF",
    "college": "College / University",
    "hometown": "Hometown, CO",
    "height": "6'1\"",
    "weight": "190",
    "bats": "L",
    "throws": "R",
    "class": "Junior",
    "major": "Major",
    "photo": "",
    "college_logo": "",
    "high_school": "",
    "action_photo": "",
    "bio": "",
    "why_tribe": "",
    "coach_comments": "",
    "development_goals": [],
    "awards": [],
    "social": {
      "instagram": "",
      "x": ""
    },
    "qa": {
      "favorite_mlb_player": "",
      "favorite_team": "",
      "favorite_baseball_memory": "",
      "walkup_song": "",
      "favorite_food": "",
      "hidden_talent": ""
    },
    "gamechanger_name": "Player Name",
    "gamechanger_player_id": ""
  },
  {
    "number": "3",
    "name": "Player Name",
    "slug": "player-3",
    "position": "RHP",
    "college": "College / University",
    "hometown": "Hometown, CO",
    "height": "6'3\"",
    "weight": "205",
    "bats": "R",
    "throws": "R",
    "class": "Sophomore",
    "major": "Major",
    "photo": "",
    "college_logo": "",
    "high_school": "",
    "action_photo": "",
    "bio": "",
    "why_tribe": "",
    "coach_comments": "",
    "development_goals": [],
    "awards": [],
    "social": {
      "instagram": "",
      "x": ""
    },
    "qa": {
      "favorite_mlb_player": "",
      "favorite_team": "",
      "favorite_baseball_memory": "",
      "walkup_song": "",
      "favorite_food": "",
      "hidden_talent": ""
    },
    "gamechanger_name": "Player Name",
    "gamechanger_player_id": ""
  },
  {
    "number": "4",
    "name": "Player Name",
    "slug": "player-4",
    "position": "C",
    "college": "College / University",
    "hometown": "Hometown, CO",
    "height": "5'11\"",
    "weight": "195",
    "bats": "R",
    "throws": "R",
    "class": "Junior",
    "major": "Major",
    "photo": "",
    "college_logo": "",
    "high_school": "",
    "action_photo": "",
    "bio": "",
    "why_tribe": "",
    "coach_comments": "",
    "development_goals": [],
    "awards": [],
    "social": {
      "instagram": "",
      "x": ""
    },
    "qa": {
      "favorite_mlb_player": "",
      "favorite_team": "",
      "favorite_baseball_memory": "",
      "walkup_song": "",
      "favorite_food": "",
      "hidden_talent": ""
    },
    "gamechanger_name": "Player Name",
    "gamechanger_player_id": ""
  },
  {
    "number": "5",
    "name": "Player Name",
    "slug": "player-5",
    "position": "LHP",
    "college": "College / University",
    "hometown": "Hometown, CO",
    "height": "6'2\"",
    "weight": "200",
    "bats": "L",
    "throws": "L",
    "class": "Freshman",
    "major": "Major",
    "photo": "",
    "college_logo": "",
    "high_school": "",
    "action_photo": "",
    "bio": "",
    "why_tribe": "",
    "coach_comments": "",
    "development_goals": [],
    "awards": [],
    "social": {
      "instagram": "",
      "x": ""
    },
    "qa": {
      "favorite_mlb_player": "",
      "favorite_team": "",
      "favorite_baseball_memory": "",
      "walkup_song": "",
      "favorite_food": "",
      "hidden_talent": ""
    },
    "gamechanger_name": "Player Name",
    "gamechanger_player_id": ""
  },
  {
    "number": "6",
    "name": "Player Name",
    "slug": "player-6",
    "position": "UTIL",
    "college": "College / University",
    "hometown": "Hometown, CO",
    "height": "6'0\"",
    "weight": "180",
    "bats": "S",
    "throws": "R",
    "class": "Senior",
    "major": "Major",
    "photo": "",
    "college_logo": "",
    "high_school": "",
    "action_photo": "",
    "bio": "",
    "why_tribe": "",
    "coach_comments": "",
    "development_goals": [],
    "awards": [],
    "social": {
      "instagram": "",
      "x": ""
    },
    "qa": {
      "favorite_mlb_player": "",
      "favorite_team": "",
      "favorite_baseball_memory": "",
      "walkup_song": "",
      "favorite_food": "",
      "hidden_talent": ""
    },
    "gamechanger_name": "Player Name",
    "gamechanger_player_id": ""
  }
]